utils_zihang/__init__.py
utils_zihang/generate_mongo_ts.py
utils_zihang/log.py
utils_zihang-0.0.7.dist-info/METADATA
utils_zihang-0.0.7.dist-info/WHEEL
utils_zihang-0.0.7.dist-info/top_level.txt
utils_zihang-0.0.7.dist-info/RECORD
