Metadata-Version: 2.1
Name: utils_zihang
Version: 0.0.7
Summary: 工具方法
Author: zihang
Author-email: clark1203@foxmail.com
Classifier: Programming Language :: Python :: 3
Classifier: License :: OSI Approved :: MIT License
Classifier: Operating System :: OS Independent
Requires-Python: >=3
Requires-Dist: loguru ==0.6.0
Requires-Dist: pymongo ==3.11.0
